sound_source_id/__init__.py
sound_source_id/__main__.py
sound_source_id/_version_info.py
sound_source_id/audio_manager.py
sound_source_id/dialog_edit_preferences.py
sound_source_id/dialog_edit_transducers.py
sound_source_id/global_parameters.py
sound_source_id/pyqtver.py
sound_source_id/qrc_resources.py
sound_source_id/sndlib.py
sound_source_id/utils.py
sound_source_id/wavpy.py
sound_source_id/wavpy_sndf.py
sound_source_id/doc/Makefile
sound_source_id/doc/calibration.rst
sound_source_id/doc/conf.py
sound_source_id/doc/experiment_setup.rst
sound_source_id/doc/index.rst
sound_source_id/doc/installation.rst
sound_source_id/doc/intro.rst
sound_source_id/doc/make.bat
sound_source_id/doc/mkdoc.sh
sound_source_id/doc/requirements.txt
sound_source_id/doc/results_files.rst
sound_source_id/doc/Figures/edit_transducers.png
sound_source_id/doc/Figures/sound_source_id_screenshot.png
sound_source_id/doc/Figures/stim_file.png
sound_source_id/doc/_build/html/.buildinfo
sound_source_id/doc/_build/html/calibration.html
sound_source_id/doc/_build/html/experiment_setup.html
sound_source_id/doc/_build/html/genindex.html
sound_source_id/doc/_build/html/index.html
sound_source_id/doc/_build/html/installation.html
sound_source_id/doc/_build/html/intro.html
sound_source_id/doc/_build/html/objects.inv
sound_source_id/doc/_build/html/results_files.html
sound_source_id/doc/_build/html/search.html
sound_source_id/doc/_build/html/searchindex.js
sound_source_id/doc/_build/html/_images/edit_transducers.png
sound_source_id/doc/_build/html/_images/sound_source_id_screenshot.png
sound_source_id/doc/_build/html/_images/stim_file.png
sound_source_id/doc/_build/html/_sources/calibration.rst.txt
sound_source_id/doc/_build/html/_sources/experiment_setup.rst.txt
sound_source_id/doc/_build/html/_sources/index.rst.txt
sound_source_id/doc/_build/html/_sources/installation.rst.txt
sound_source_id/doc/_build/html/_sources/intro.rst.txt
sound_source_id/doc/_build/html/_sources/results_files.rst.txt
sound_source_id-0.2.8.dist-info/COPYING.txt
sound_source_id-0.2.8.dist-info/METADATA
sound_source_id-0.2.8.dist-info/WHEEL
sound_source_id-0.2.8.dist-info/entry_points.txt
sound_source_id-0.2.8.dist-info/top_level.txt
sound_source_id-0.2.8.dist-info/RECORD
