Metadata-Version: 2.1
Name: sound_source_id
Version: 0.2.8
Summary: Python application for running sound localization experiments
Author-email: Samuele Carcagno <sam.carcagno@gmail.com>
License: GNU GENERAL PUBLIC LICENSE
Project-URL: Homepage, https://gitlab.com/sam81/sound_source_id
Project-URL: Bug Tracker, https://gitlab.com/sam81/sound_source_id/-/issues
Classifier: Programming Language :: Python :: 3
Classifier: License :: OSI Approved :: GNU General Public License v3 (GPLv3)
Classifier: Operating System :: OS Independent
Classifier: Development Status :: 3 - Alpha
Classifier: Environment :: X11 Applications :: Qt
Classifier: Intended Audience :: Developers
Classifier: Operating System :: MacOS :: MacOS X
Classifier: Operating System :: Microsoft :: Windows
Classifier: Operating System :: POSIX
Classifier: Topic :: Scientific/Engineering
Requires-Python: >=3.7
License-File: COPYING.txt
Requires-Dist: matplotlib >=3.0.0
Requires-Dist: numpy >=1.0.0
Requires-Dist: pandas >=1.0.0
Requires-Dist: PyAudio >=0.2.11
Requires-Dist: PyQt6 >=6.6.0
Requires-Dist: scipy >=1.0.1
Requires-Dist: pysofaconventions >=0.1.1
Requires-Dist: netCDF4 >=1.0.0
